MANIFEST.in
README.md
requirements.txt
setup.py
ai_jsonable.egg-info/PKG-INFO
ai_jsonable.egg-info/SOURCES.txt
ai_jsonable.egg-info/dependency_links.txt
ai_jsonable.egg-info/entry_points.txt
ai_jsonable.egg-info/requires.txt
ai_jsonable.egg-info/top_level.txt
aijson/__init__.py
aijson/__main__.py
aijson/build.py
aijson/decorate.py
aijson/program.py
aijson/version.py
example/__init__.py
example/config.py
example/rebuild.py
example/themod.py