Metadata-Version: 2.1
Name: ai-jsonable
Version: 0.0.1
Summary: Tracking model parameters and settings for AI using JSON.
Home-page: https://github.com/blythed/aijson
Author: Duncan Blythe
Author-email: duncanblythe@gmail.com
License: MIT License
Classifier: Programming Language :: Python :: 3.6
Classifier: Programming Language :: Python :: 3.7
Classifier: Programming Language :: Python :: 3.8
Classifier: Programming Language :: Python :: 3.9
Classifier: Topic :: Scientific/Engineering
Classifier: Topic :: Scientific/Engineering :: Artificial Intelligence
Requires-Python: >=3.6
